{
    "list":[{
            "img":"http://static.asus.com.cn/store/20180828/23275357981001.jpg",
            "title":"灵耀S 2代",
            "text":"三面窄边框 炫彩轻薄",
            "Price":"￥5699",
            "ago":"￥6099"
        },
        {
            "img":"http://static.asus.com.cn/store/album/images/U4EM7R3LDY7Z03/10322456985110.png",
            "title":"A豆笔记本",
            "text":"13.3英寸 全面屏",
            "Price":"￥3699",
            "ago":"￥3999"
        },
        {
            "img":"https://static.asus.com.cn/store/album/images/BWUHW3C5J917G9/14552398485356.jpg",
            "title":"ROG枪神2S Plus",
            "text":"RTX™2070 17.3''IPS屏",
            "Price":"￥16999",
            "ago":"￥16999"
        },
        {
            "img":"https://static.asus.com.cn/store/album/images/BWUHW3C5J917G9/14552398485356.jpg",
            "title":"新ROG枪神2S",
            "text":"RTX™2070 15.6''IPS屏",
            "Price":"￥15999",
            "ago":"￥15999"
        },
        {
            "img":"http://static.asus.com.cn/store/album/images/A4M8VDDL84Y96F/10403248495748.jpg",
            "title":"灵耀U 2代-14寸",
            "text":"IPS全镜面屏 人脸识别",
            "Price":"￥6799",
            "ago":"￥7099"
        },
        {
            "img":"http://static.asus.com.cn/store/20180912/17455854544956.jpg",
            "title":"飞行堡垒6 火陨版",
            "text":"超窄边框 八代标压",
            "Price":"￥6299",
            "ago":"￥6299"
        },
        {
            "img":"https://static.asus.com.cn/store/20181012/17151753485657.jpg",
            "title":"ROG冰刃3",
            "text":"15.6''IPS屏 便携猛兽",
            "Price":"￥15999",
            "ago":"￥17999"
        },
        {
            "img":"https://static.asus.com.cn/store/20180828/23284949100559.jpg",
            "title":"灵耀U4100UN",
            "text":"超窄边框 72%高色域",
            "Price":"￥7399",
            "ago":"￥8399"
        },
        {
            "img":"https://static.asus.com.cn/store/20180828/23403450505110.jpg",
            "title":"新顽石5代游戏本",
            "text":"八代处理器 高清大屏",
            "Price":"￥4399",
            "ago":"￥4799"
        },
        {
            "img":"https://static.asus.com.cn/store/20180912/17442697995650.jpg",
            "title":"灵耀X Pro双屏笔记本",
            "text":"纤薄微边框 双重显示",
            "Price":"￥13999",
            "ago":"￥14199"
        },
        {
            "img":"https://static.asus.com.cn/store/album/images/N204TW04IN1LXO/11315155559997.jpg",
            "title":"顽石Y406UA",
            "text":"四面窄边 小翘跟设计",
            "Price":"￥43999",
            "ago":"￥5199"
        },
        {
            "img":"http://static.asus.com.cn/store/album/images/U4EM7R3LDY7Z03/10322456985110.png",
            "title":"A豆笔记本",
            "text":"13.3英寸 全面屏",
            "Price":"￥5199",
            "ago":"￥5499"
        },
        {
            "img":"http://static.asus.com.cn/store/20180829/00020499579810.jpg",
            "title":"ROG枪神2",
            "text":"专为FPS电竞射手打造",
            "Price":"￥12999",
            "ago":"￥16999"
        },
        {
            "img":"http://static.asus.com.cn/store/20180829/00020499579810.jpg",
            "title":"ROG枪神2",
            "text":"专为FPS电竞射手打造",
            "Price":"￥10999",
            "ago":"￥13999"
        },
        {
            "img":"http://static.asus.com.cn/store/album/images/U4EM7R3LDY7Z03/10322456985110.png",
            "title":"A豆笔记本",
            "text":"13.3英寸 全面屏",
            "Price":"￥4799",
            "ago":"￥5099"
        }
    ]
}

